[
  {
    "id": "muzzle_brake_precision_hypertap",
    "copy-from": "muzzle_brake_abstract",
    "type": "GUNMOD",

    "//sources": [
      "https://www.wingtactical.com/firearm-parts/ar-15-parts/muzzle-devices/precision-armament-hypertap-muzzle-brake-5-56-223/"
    ],

    "name": {
      "str": "Precision Armament Hypertap muzzle brake"
    },
    "description": "TBD",

    "weight": "87 g",
    "volume": "24 ml",
    "longest_side": "65 mm",

    "//calibers": ["556"],

    "//recoil_reduction": "84%",
    "handling_modifier": 42,

    "price": "180 USD"
  },

  {
    "id": "muzzle_brake_sjc_titan",
    "copy-from": "muzzle_brake_abstract",
    "type": "GUNMOD",

    "//sources": ["https://stores.sjcguns.com/223-5-56-sjc-titan-cs-black/"],

    "name": {
      "str": "S&J Customs Titan muzzle brake"
    },
    "description": "TBD",

    "weight": "87 g",
    "volume": "33 ml",
    "longest_side": "70 mm",

    "//calibers": ["556"],

    "//recoil_reduction": "78%",
    "//recoil_distance": "2.4688 in",
    "handling_modifier": 39,

    "price": "100 USD"
  },

  {
    "id": "muzzle_brake_v7",
    "copy-from": "muzzle_brake_abstract",
    "type": "GUNMOD",

    "//sources": [
      "https://www.vsevenweaponsystems.com/muzzle-devices/v7-muzzle-brake",
      "https://www.thetruthaboutguns.com/ar-15-muzzle-brake-shootout-3/"
    ],

    "name": {
      "str": "V Seven muzzle brake"
    },
    "description": "TBD",

    "weight": "76 g",
    "volume": "22 ml",
    "longest_side": "53 mm",

    "material": ["steel"],

    "//calibers": ["556"],

    "//recoil_reduction": "56.35%",
    "//recoil_distance": "4.9375 in.",
    "handling_modifier": 28,

    "//price": "for the 5/8 × 24 / satin stainless model",
    "price": "97 USD"
  },

  {
    "id": "muzzle_brake_v7_furion",
    "copy-from": "muzzle_brake_abstract",
    "type": "GUNMOD",

    "//sources": [
      "https://www.vsevenweaponsystems.com/muzzle-devices/furion/",
      "https://www.thetruthaboutguns.com/ar-15-muzzle-brake-shootout-3/"
    ],

    "name": {
      "str": "V Seven FURION muzzle brake"
    },
    "description": "TBD",

    "weight": "47 g",
    "//trim": "trimmed slightly for empty spaces",
    "volume": "24 ml",
    "longest_side": "58 mm",

    "material": ["titanium"],

    "//calibers": ["556"],

    "//recoil_reduction": "64.36%",
    "//recoil_distance": "4.0313 in.",
    "handling_modifier": 32,

    "//price": "for the titanium 5.56mm model",
    "price": "153 USD"
  },

  {
    "id": "muzzle_brake_apex_esa",
    "copy-from": "muzzle_brake_abstract",
    "type": "GUNMOD",

    "//sources": [
      "https://www.apextactical.com/apex-enhanced-stabilization-attachment",
      "https://www.thetruthaboutguns.com/ar-15-muzzle-brake-shootout-3/"
    ],

    "name": {
      "str": "Apex Tactical ESA muzzle brake"
    },
    "description": "TBD",

    "weight": "63 g",
    "//trim": "trimmed slightly for empty spaces",
    "volume": "17 ml",
    "longest_side": "66 mm",

    "//calibers": ["556"],

    "//recoil_reduction": "60.50%",
    "//recoil_distance": "4.4688 in.",
    "handling_modifier": 30,

    "//price": "for the square design",
    "price": "90 USD"
  },

  {
    "id": "muzzle_brake_dead_air_keymount",
    "copy-from": "muzzle_brake_abstract",
    "type": "GUNMOD",

    "//sources": [
      "https://deadairsilencers.com/product/keymount-muzzle-brake/",
      "https://www.thetruthaboutguns.com/ar-15-muzzle-brake-shootout-3/",
      "https://deadairsilencers.com/dead-air-armament-shipping-keymount-muzzle-brake-for-sandman-suppressors-2/"
    ],

    "name": {
      "str": "Dead Air KeyMount muzzle brake"
    },
    "description": "TBD",

    "weight": "116 g",
    "//trim": "trimmed slightly for empty spaces",
    "volume": "37 ml",
    "longest_side": "66 mm",

    "//calibers": ["556"],

    "//recoil_reduction": "56.63%",
    "//recoil_distance": "4.9063 in.",
    "handling_modifier": 28,

    "price": "89 USD"
  },

  {
    "id": "muzzle_brake_thunder_beast_sr",
    "copy-from": "muzzle_brake_abstract",
    "type": "GUNMOD",

    "//sources": [
      "https://thunderbeastarms.com/products/dominus-sr",
      "https://thunderbeastarms.com/products/accessories",
      "https://escapefromtarkov.fandom.com/wiki/AR-15_Thunder_Beast_Arms_223CB_5.56x45_muzzle_brake",
      "https://www.thetruthaboutguns.com/ar-15-muzzle-brake-shootout-3/"
    ],

    "name": {
      "str": "Thunder Beast Arms SR muzzle brake"
    },
    "description": "TBD",

    "//weight": "Dominus SR description states the weight of the brake to be 3.5 oz ≈ 100 g",
    "weight": "100 g",
    "//dimensions": "2.86 (approximate from visual reference) × 1.53 (diameter of Dominus SR - 15%) in.",
    "//trim": "10% trim for shape",
    "volume": "77 ml",
    "longest_side": "73 mm",

    "//calibers": ["556"],

    "//recoil_reduction": "???",
    "//handling_modifier": "its 5.56mm cousin reduces recoil by 72.93%, so let's assume this one performs only slightly worse, at a completely-fictional 70.62%",
    "handling_modifier": 35,

    "add_mod": [["Thunder Beast SR mount", 1]],

    "price": "145 USD"
  }
]
